odoo10_addon_stock_available_sale-10.0.1.0.1-py3.8-nspkg.pth
odoo/addons/stock_available_sale/README.rst
odoo/addons/stock_available_sale/__init__.py
odoo/addons/stock_available_sale/__manifest__.py
odoo/addons/stock_available_sale/i18n/ca.po
odoo/addons/stock_available_sale/i18n/cs_CZ.po
odoo/addons/stock_available_sale/i18n/de.po
odoo/addons/stock_available_sale/i18n/el_GR.po
odoo/addons/stock_available_sale/i18n/es.po
odoo/addons/stock_available_sale/i18n/es_ES.po
odoo/addons/stock_available_sale/i18n/es_MX.po
odoo/addons/stock_available_sale/i18n/eu.po
odoo/addons/stock_available_sale/i18n/fi.po
odoo/addons/stock_available_sale/i18n/fr.po
odoo/addons/stock_available_sale/i18n/fr_CH.po
odoo/addons/stock_available_sale/i18n/fr_FR.po
odoo/addons/stock_available_sale/i18n/gl.po
odoo/addons/stock_available_sale/i18n/hr.po
odoo/addons/stock_available_sale/i18n/hr_HR.po
odoo/addons/stock_available_sale/i18n/it.po
odoo/addons/stock_available_sale/i18n/nl.po
odoo/addons/stock_available_sale/i18n/nl_NL.po
odoo/addons/stock_available_sale/i18n/pt.po
odoo/addons/stock_available_sale/i18n/pt_BR.po
odoo/addons/stock_available_sale/i18n/ro.po
odoo/addons/stock_available_sale/i18n/ru.po
odoo/addons/stock_available_sale/i18n/sl.po
odoo/addons/stock_available_sale/i18n/stock_available_sale.pot
odoo/addons/stock_available_sale/i18n/tr.po
odoo/addons/stock_available_sale/i18n/tr_TR.po
odoo/addons/stock_available_sale/i18n/vi_VN.po
odoo/addons/stock_available_sale/i18n/zh_CN.po
odoo/addons/stock_available_sale/models/__init__.py
odoo/addons/stock_available_sale/models/product_product.py
odoo/addons/stock_available_sale/models/product_template.py
odoo/addons/stock_available_sale/static/description/icon.png
odoo/addons/stock_available_sale/tests/__init__.py
odoo/addons/stock_available_sale/tests/test_quoted_qty.py
odoo/addons/stock_available_sale/views/product_template_view.xml
odoo10_addon_stock_available_sale-10.0.1.0.1.dist-info/METADATA
odoo10_addon_stock_available_sale-10.0.1.0.1.dist-info/WHEEL
odoo10_addon_stock_available_sale-10.0.1.0.1.dist-info/namespace_packages.txt
odoo10_addon_stock_available_sale-10.0.1.0.1.dist-info/top_level.txt
odoo10_addon_stock_available_sale-10.0.1.0.1.dist-info/RECORD
